Metadata-Version: 2.1
Name: orpl
Version: 22313
Summary: The fork of simpledemotivators
Home-page: https://github.com/Daemon-RE/openre-pylib
Author: OpenRE
Author-email: admin@w102018tv.xyz
License: UNKNOWN
Platform: UNKNOWN
Classifier: Programming Language :: Python :: 3.6
Classifier: Programming Language :: Python :: 3.7
Classifier: Operating System :: OS Independent
